drode/__init__.py
drode/adapters/__init__.py
drode/adapters/aws.py
drode/adapters/drone.py
drode/config.py
drode/entrypoints/__init__.py
drode/entrypoints/cli.py
drode/py.typed
drode/services.py
drode/version.py
drode/views.py
drode-1.3.0.dist-info/entry_points.txt
drode-1.3.0.dist-info/WHEEL
drode-1.3.0.dist-info/METADATA
drode-1.3.0.dist-info/licenses/LICENSE
drode-1.3.0.dist-info/RECORD
