Metadata-Version: 2.1
Name: drode
Version: 1.3.0
Summary: Wrapper over the Drone and AWS APIs to make deployments more user friendly.
License: GPL-3.0-only
Author-email: Lyz <lyz-code-security-advisories@riseup.net>
Requires-Python: >=3.7
Classifier: Development Status :: 2 - Pre-Alpha
Classifier: Intended Audience :: Developers
Classifier: License :: OSI Approved :: GNU General Public License v3 (GPLv3)
Classifier: Natural Language :: English
Classifier: Operating System :: POSIX
Classifier: Operating System :: Unix
Classifier: Programming Language :: Python
Classifier: Programming Language :: Python :: 3
Classifier: Programming Language :: Python :: 3.10
Classifier: Programming Language :: Python :: 3.7
Classifier: Programming Language :: Python :: 3.8
Classifier: Programming Language :: Python :: 3.9
Classifier: Topic :: Utilities
Requires-Dist: boto3>=1.21.32
Requires-Dist: click>=8.1.3
Requires-Dist: goodconf[yaml]>=2.0.1
Requires-Dist: requests>=2.27.1
Requires-Dist: tabulate>=0.8.9
Project-URL: Issues, https://github.com/lyz-code/drode/issues
Project-URL: documentation, https://lyz-code.github.io/drode
Project-URL: homepage, https://github.com/lyz-code/drode
